fastflow/__init__.py
pyfastflow-0.0.1.dist-info/LICENSE
pyfastflow-0.0.1.dist-info/METADATA
pyfastflow-0.0.1.dist-info/WHEEL
pyfastflow-0.0.1.dist-info/top_level.txt
pyfastflow-0.0.1.dist-info/RECORD
